promptflow_custom_tools/__init__.py
promptflow_custom_tools/tools/__init__.py
promptflow_custom_tools/tools/claude.py
promptflow_custom_tools/tools/perplexity.py
promptflow_custom_tools/tools/utils.py
promptflow_custom_tools/yamls/claude.yaml
promptflow_custom_tools/yamls/perplexity.yaml
tests/__init__.py
tests/test_claude.py
tests/test_perplexity.py
promptflow_custom_tools-0.1.3.dist-info/LICENSE
promptflow_custom_tools-0.1.3.dist-info/METADATA
promptflow_custom_tools-0.1.3.dist-info/WHEEL
promptflow_custom_tools-0.1.3.dist-info/entry_points.txt
promptflow_custom_tools-0.1.3.dist-info/top_level.txt
promptflow_custom_tools-0.1.3.dist-info/RECORD
