Metadata-Version: 2.1
Name: promptflow-custom-tools
Version: 0.1.3
Summary: This is my tools package
License-File: LICENSE
Requires-Dist: promptflow
Requires-Dist: promptflow-tools
Requires-Dist: anthropic
Requires-Dist: requests
